heavyai/__init__.py
heavyai/_loaders.py
heavyai/_mutators.py
heavyai/_pandas_loaders.py
heavyai/_transforms.py
heavyai/_utils.py
heavyai/connection.py
heavyai/ipc.py
heavyai-1.2.dist-info/LICENSE.md
heavyai-1.2.dist-info/WHEEL
heavyai-1.2.dist-info/METADATA
heavyai-1.2.dist-info/RECORD
