Metadata-Version: 2.1
Name: heavyai
Version: 1.2
Summary: Data science toolkit support for HeavyDB
Author-email: "Heavy.AI" <community@heavy.ai>
Requires-Python: >=3.7
Classifier: License :: OSI Approved :: Apache Software License
Classifier: Topic :: Database
Classifier: Topic :: Scientific/Engineering
Requires-Dist: pyheavydb >=6.0.0
Requires-Dist: pyarrow >=3.0.0
Requires-Dist: pandas
Requires-Dist: numpy
Requires-Dist: shapely
Requires-Dist: importlib_metadata
Requires-Dist: heavyai[doc] ; extra == "dev"
Requires-Dist: heavyai[test] ; extra == "dev"
Requires-Dist: pre-commit ; extra == "dev"
Requires-Dist: flit ; extra == "dev"
Requires-Dist: sphinx ; extra == "doc"
Requires-Dist: numpydoc ; extra == "doc"
Requires-Dist: sphinx-rtd-theme ; extra == "doc"
Requires-Dist: numba >=0.49 ; extra == "gpu"
Requires-Dist: pytest ; extra == "test"
Requires-Dist: coverage ; extra == "test"
Requires-Dist: pytest-mock ; extra == "test"
Requires-Dist: geopandas ; extra == "test"
Project-URL: Home, https://github.com/heavyai/heavyai
Project-URL: Source, https://github.com/heavyai/heavyai
Provides-Extra: dev
Provides-Extra: doc
Provides-Extra: gpu
Provides-Extra: test
